ghat/__init__.py
ghat/__main__.py
ghat/ghat.html
ghat/ghat.js
ghat/ghat_main.py
ghat-0.1.3.dist-info/LICENSE.txt
ghat-0.1.3.dist-info/METADATA
ghat-0.1.3.dist-info/WHEEL
ghat-0.1.3.dist-info/entry_points.txt
ghat-0.1.3.dist-info/top_level.txt
ghat-0.1.3.dist-info/RECORD
