Metadata-Version: 2.1
Name: ghat
Version: 0.1.3
Summary: A quick hack for decorating your GitHub contribution calendar through a specific date file.
Home-page: https://github.com/Nymphxyz/ghat
Author: Nymphxyz
Author-email: xyz.hack666@gmail.com
License: MIT
Platform: UNKNOWN
